tap_mysql/__init__.py
tap_mysql/client.py
tap_mysql/tap.py
meltanolabs_tap_mysql-0.0.1a1.dist-info/METADATA
meltanolabs_tap_mysql-0.0.1a1.dist-info/WHEEL
meltanolabs_tap_mysql-0.0.1a1.dist-info/entry_points.txt
meltanolabs_tap_mysql-0.0.1a1.dist-info/RECORD
