Metadata-Version: 2.1
Name: meltanolabs-tap-mysql
Version: 0.0.1a1
Summary: `tap-mysql` is a Singer tap for mysql, built with the Meltano Singer SDK.
Home-page: https://meltano.com
License: MIT
Keywords: MySQL,Vitess,PlanetScale,Singer,ELT,Meltano,Meltano SDK
Author: Meltano Team and Contributors
Author-email: hello@meltano.com
Maintainer: Meltano Team and Contributors
Maintainer-email: hello@meltano.com
Requires-Python: >=3.8
Classifier: Intended Audience :: Developers
Classifier: License :: OSI Approved :: MIT License
Classifier: Operating System :: OS Independent
Classifier: Programming Language :: Python :: 3
Classifier: Programming Language :: Python :: 3.8
Classifier: Programming Language :: Python :: 3.9
Classifier: Programming Language :: Python :: 3.10
Classifier: Programming Language :: Python :: 3.11
Classifier: Programming Language :: Python :: 3.12
Classifier: Programming Language :: Python :: Implementation :: CPython
Provides-Extra: binary
Provides-Extra: s3
Requires-Dist: fs-s3fs (==1.1.1) ; extra == "s3"
Requires-Dist: mysqlclient (==2.2.4) ; extra == "binary"
Requires-Dist: pymysql (==1.1.0)
Requires-Dist: singer-sdk (>=0.35.2,<0.36.0)
Requires-Dist: sqlalchemy (<2)
Requires-Dist: sshtunnel (==0.4.0)
Project-URL: Repository, https://github.com/meltanolabs/tap-mysql
